azure/mgmt/containerservice/__init__.py
azure/mgmt/containerservice/_configuration.py
azure/mgmt/containerservice/_container_service_client.py
azure/mgmt/containerservice/_serialization.py
azure/mgmt/containerservice/_version.py
azure/mgmt/containerservice/models.py
azure/mgmt/containerservice/py.typed
azure/mgmt/containerservice/aio/__init__.py
azure/mgmt/containerservice/aio/_configuration.py
azure/mgmt/containerservice/aio/_container_service_client.py
azure/mgmt/containerservice/v2017_07_01/__init__.py
azure/mgmt/containerservice/v2017_07_01/_configuration.py
azure/mgmt/containerservice/v2017_07_01/_container_service_client.py
azure/mgmt/containerservice/v2017_07_01/_patch.py
azure/mgmt/containerservice/v2017_07_01/_version.py
azure/mgmt/containerservice/v2017_07_01/py.typed
azure/mgmt/containerservice/v2017_07_01/_utils/__init__.py
azure/mgmt/containerservice/v2017_07_01/_utils/serialization.py
azure/mgmt/containerservice/v2017_07_01/aio/__init__.py
azure/mgmt/containerservice/v2017_07_01/aio/_configuration.py
azure/mgmt/containerservice/v2017_07_01/aio/_container_service_client.py
azure/mgmt/containerservice/v2017_07_01/aio/_patch.py
azure/mgmt/containerservice/v2017_07_01/aio/operations/__init__.py
azure/mgmt/containerservice/v2017_07_01/aio/operations/_container_services_operations.py
azure/mgmt/containerservice/v2017_07_01/aio/operations/_patch.py
azure/mgmt/containerservice/v2017_07_01/models/__init__.py
azure/mgmt/containerservice/v2017_07_01/models/_container_service_client_enums.py
azure/mgmt/containerservice/v2017_07_01/models/_models_py3.py
azure/mgmt/containerservice/v2017_07_01/models/_patch.py
azure/mgmt/containerservice/v2017_07_01/operations/__init__.py
azure/mgmt/containerservice/v2017_07_01/operations/_container_services_operations.py
azure/mgmt/containerservice/v2017_07_01/operations/_patch.py
azure/mgmt/containerservice/v2019_09_30_preview/__init__.py
azure/mgmt/containerservice/v2019_09_30_preview/_configuration.py
azure_mgmt_containerservice-38.0.0.dist-info/LICENSE
azure_mgmt_containerservice-38.0.0.dist-info/METADATA
azure_mgmt_containerservice-38.0.0.dist-info/WHEEL
azure_mgmt_containerservice-38.0.0.dist-info/top_level.txt
azure_mgmt_containerservice-38.0.0.dist-info/RECORD
